[
  {
  "year": "2018-2019",
  "programs": [
    {
      "label": "Юный экскурсовод. Баштырева",
      "link": "https://drive.google.com/open?id=1A6tb820y_BkNVUlKUP6u_lImDgXmITqB"
    },
    {
      "label": "Моя малая Родина. Бойкова",
      "link": "https://drive.google.com/open?id=1LTwLhV2Z4rM3fUtybxb5gAgQ4Q2zcx0X"
    },
    {
      "label": "Юный турист-ориентировщик. Смуров",
      "link": "https://drive.google.com/open?id=1lroWTTlZ-iWYhaH8f6covyN2on0mykSm"
    }
  ],
  "common": [
    {
      "label": "Учебный план на 2018-2019",
      "link": "https://drive.google.com/open?id=1JGqVRZYxq1NuqSFri7kAEx5UznZLZuRD"
    },
    {
      "label": "Учебный план на с 1 февраля",
      "link": "https://drive.google.com/open?id=1DWO7IfzK_XqMSXBtFBKBXorzi8cYYCxB"
    },
    {
      "label": "Календарный учебный график",
      "link": "https://drive.google.com/open?id=1Obg4DQcKm9sVnTHOoDzZ6itth4APOv8d"
    },
    {
      "label": "Реализуемые дополнительные программы",
      "link": "https://drive.google.com/open?id=1RCRGTCzvtxOzyUQ4ccWzmX27ZgfaA5jU"
    },
    {
      "label": "Методические рекомендации по расследованию несчастных случаев",
      "link": "https://drive.google.com/open?id=1ywyl0uFP4IL3VxUDJ5QmhPVHrLi5jMoK"
    },
    {
      "label": "Об утверждении Правил организованной перевозки группы детей автобусами",
      "link": "https://drive.google.com/open?id=1ZhLK45cOqTEgmcmmPTVZzyBqy4Fm5XdI"
    },
    {
      "label": "Методические рекомендации по реализации доп.программ",
      "link": "https://drive.google.com/open?id=1HL-gBm43CkjQuvMOskAcgDcD3qjll6CE"
    }
  ],
  "achievements": []
},
  {
    "year": "2017-2018",
    "programs": [
      {
        "label": "Юный экскурсовод. Баштырева",
        "link": "https://drive.google.com/file/d/1FoS-APxzWKBDNiXb8KDxGAYKQKQLHLiX/view?usp=sharing"
      },
      {
        "label": "Моя малая Родина. Бойкова",
        "link": "https://drive.google.com/open?id=1fT3U69PBWFFmL5gEYczcLwqSRHC8YK_H"
      },
      {
        "label": "Техника пешеходного туризма. Лукьянова",
        "link": "https://drive.google.com/file/d/14TAn91TowKPXyXqEFap10oRfZPD5ifxZ/view?usp=sharing"
      },
      {
        "label": "Юный турист-ориентировщик. Смуров",
        "link": "https://drive.google.com/file/d/13KS2f9zXQwznL0n1mfd3ue95EHqmF7Cy/view?usp=sharing"
      }
    ],
    "common": [
      {
        "label": "Учебный план на 2017-2018",
        "link": "https://drive.google.com/open?id=1TKE4IMaLugiF74fqKXgEHsWNMT5xYwai"
      },
      {
        "label": "Расписание 2017-2018 1-е полугодие",
        "link": "https://drive.google.com/file/d/1toJsoXBRr2FDTr5QSf_-8H6BBgsl8n6g/view?usp=sharing"
      },
      {
        "label": "Расписание 2017-2018 2-е полугодие",
        "link": "https://drive.google.com/file/d/1_xX9EkwoZwtkQK2uGWxUG3l5kpKaG2Lj/view?usp=sharing"
      },
      {
        "label": "Решение городской думы. Баштырева",
        "link": "https://drive.google.com/file/d/1Dz2kvGDuzG8rvM2HXazbeaDj8HZA-Mx-/view?usp=sharing"
      },
      {
        "label": "Решение городской думы. Смурнов",
        "link": "https://drive.google.com/file/d/1ONb7lY_MJoiTekKfW4W4JgDyf8lAKu-l/view?usp=sharing"
      }
    ],
    "achievements": []
  },
  {
    "year": "2016-2017",
    "programs": [
      {
        "label": "Моя малая Родина. Бойкова",
        "link": "https://drive.google.com/open?id=140Q1uv_PN2AVP4F5gussQvwOVetkPctH"
      },
      {
        "label": "Юный турист-ориентировщик. Смуров",
        "link": "https://drive.google.com/file/d/0B4Y-eduzf4rjZlkxWFZEc0tDeGM/view?usp=sharing"
      },
      {
        "label": "Техника пешеходного туризма 240ч. Лукьянова",
        "link": "https://drive.google.com/file/d/0B4Y-eduzf4rjSW00TnJZYWtmTlE/view?usp=sharing"
      },
      {
        "label": "Техника пешеходного туризма 120ч. Лукьянова",
        "link": "https://drive.google.com/file/d/0B4Y-eduzf4rja3VnYVgxOUhsZmc/view?usp=sharing"
      },
      {
        "label": "Юный экскурсовод. Баштырева",
        "link": "https://drive.google.com/open?id=1bkEL3NodQ8j7bz4XDC_wqhONBI9kxu4t"
      }
    ],
    "common": [
      {
        "label": "Учебный план на 2016-2017",
        "link": "https://drive.google.com/file/d/0B4Y-eduzf4rjbjRxNDRCelprVHM/view?usp=sharing"
      },
      {
        "label": "Расписание 2016-2017",
        "link": "https://drive.google.com/file/d/0B4Y-eduzf4rjSjdmNVJSU2hUSmc/view?usp=sharing"
      },
      {
        "label": "Расписание 2016-2017 2-е полугодие",
        "link": "https://drive.google.com/file/d/0B4Y-eduzf4rjRVdJcVZZbWhUWHM/view?usp=sharing"
      },
      {
        "label": "Количество обучающихся",
        "link": "https://drive.google.com/file/d/0B4Y-eduzf4rjM0MzX3VZQ19fdGM/view?usp=sharing"
      }
    ],
    "achievements": [
      {
        "label": "Педагог Лукьянова Я.Ю.: Диплом. Награждается Кунгис Георгий за 2 место в открытых городских соревнованиях по технике пешеходного туризма в закрытых помещениях, среди юношей 2001-02 г.р., на дистанции 1-го класса. Благодарственное письмо Лукьяновой Яне Юрьевне за активное участие в праздничных мероприятиях, посвященных 72-ой годовщины Победы в Великой Отечественной войне 1941-1945 гг.",
        "link": "https://pp.userapi.com/c836425/v836425908/41c2a/tm5y6PcfLZs.jpg"
      },
      {
        "label": "Педагог Бойкова О.В.: Диплом. Награждается Селякова Мария за 3 место в открытых городских соревнованиях по технике пешеходного туризма в закрытых помещениях, среди девушек 2005-06 г.р., на дистанции 1-го класса.",
        "link": "https://pp.userapi.com/c836425/v836425908/41c3d/qWRA0xfdbWg.jpg"
      }
    ]
  },
  {
    "year": "2015-2016",
    "programs": [
      {
        "label": "Юный экскурсовод. Баштырева",
        "link": "https://drive.google.com/open?id=1tcNIZOpcnNh0iSAPTPPs9e3rog3vNcv0"
      },
      {
        "label": "Моя малая Родина. Бойкова",
        "link": "https://drive.google.com/open?id=1S3YEFJ5qLdmsWFLeF-TXL-lfZm5MjQ9H"
      },
      {
        "label": "Улицы родного города. Никонова",
        "link": "https://drive.google.com/open?id=1gIXNpmg5E_33mAOqOP9aSIT9Kgo0jnf9"
      },
      {
        "label": "Техника пешеходного туризма. Беляков",
        "link": "https://drive.google.com/file/d/0B4Y-eduzf4rjclNiUk96alVkQ0E/view?usp=sharing"
      },
      {
        "label": "Активисты школьного музея. Ильина",
        "link": "https://drive.google.com/open?id=1jDOTJV3gt1zNCwIjGzh0DBuzbGzyaFrB"
      },
      {
        "label": "Я познаю свой край. Сторожко",
        "link": "https://drive.google.com/open?id=1s9sWao_WEqo8z_jwyxeO9mH_tPFy3MND"
      },
      {
        "label": "Юный экскурсовод, 11-13 лет. Владимирова",
        "link": "https://drive.google.com/open?id=1P2rlGANvSvxgXrjAcCL7lvl0jk3lK0WV"
      },
      {
        "label": "Юный экскурсовод, 14-15 лет. Владимирова",
        "link": "https://drive.google.com/open?id=1u-YUxy-lPHhYVCzfy9LhnUnCX89Ah2Pp"
      }
    ],
    "common": [
      {
        "label": "Учебный план на 1 полугодие 2015-2016",
        "link": "https://drive.google.com/file/d/0B4Y-eduzf4rjVkxTYk1xVjc4bTA/view?usp=sharing"
      },
      {
        "label": "Учебный план на 2 полугодие 2015-2016",
        "link": "https://drive.google.com/file/d/0B4Y-eduzf4rjTzlzV0pBSmF4NVk/view?usp=sharing"
      }
    ],
    "achievements": []
  }
]
